{
  "id": "ru-lv-a1",
  "name": "Russian-Latvian A1",
  "description": "~200 basic survival words for absolute beginners. Covers greetings, numbers, colours, family, food, days, months, and the most common verbs.",
  "sourceCode": "ru",
  "targetCode": "lv",
  "level": "A1",
  "words": [
    {
      "source": "привет",
      "target": "sveiki",
      "tags": ["greetings", "A1"]
    },
    {
      "source": "пока",
      "target": "čau",
      "tags": ["greetings", "A1"]
    },
    {
      "source": "до свидания",
      "target": "ardievu",
      "tags": ["greetings", "A1"]
    },
    {
      "source": "пожалуйста",
      "target": "lūdzu",
      "tags": ["greetings", "A1"]
    },
    {
      "source": "спасибо",
      "target": "paldies",
      "tags": ["greetings", "A1"]
    },
    {
      "source": "да",
      "target": "jā",
      "tags": ["greetings", "A1"]
    },
    {
      "source": "нет",
      "target": "nē",
      "tags": ["greetings", "A1"]
    },
    {
      "source": "извините",
      "target": "piedodiet",
      "tags": ["greetings", "A1"]
    },
    {
      "source": "доброе утро",
      "target": "labrīt",
      "tags": ["greetings", "A1"]
    },
    {
      "source": "добрый день",
      "target": "labdien",
      "tags": ["greetings", "A1"]
    },
    {
      "source": "добрый вечер",
      "target": "labvakar",
      "tags": ["greetings", "A1"]
    },
    {
      "source": "до встречи",
      "target": "uz redzēšanos",
      "tags": ["greetings", "A1"]
    },
    {
      "source": "один",
      "target": "viens",
      "tags": ["numbers", "A1"]
    },
    {
      "source": "два",
      "target": "divi",
      "tags": ["numbers", "A1"]
    },
    {
      "source": "три",
      "target": "trīs",
      "tags": ["numbers", "A1"]
    },
    {
      "source": "четыре",
      "target": "četri",
      "tags": ["numbers", "A1"]
    },
    {
      "source": "пять",
      "target": "pieci",
      "tags": ["numbers", "A1"]
    },
    {
      "source": "шесть",
      "target": "seši",
      "tags": ["numbers", "A1"]
    },
    {
      "source": "семь",
      "target": "septiņi",
      "tags": ["numbers", "A1"]
    },
    {
      "source": "восемь",
      "target": "astoņi",
      "tags": ["numbers", "A1"]
    },
    {
      "source": "девять",
      "target": "deviņi",
      "tags": ["numbers", "A1"]
    },
    {
      "source": "десять",
      "target": "desmit",
      "tags": ["numbers", "A1"]
    },
    {
      "source": "одиннадцать",
      "target": "vienpadsmit",
      "tags": ["numbers", "A1"]
    },
    {
      "source": "двенадцать",
      "target": "divpadsmit",
      "tags": ["numbers", "A1"]
    },
    {
      "source": "тринадцать",
      "target": "trīspadsmit",
      "tags": ["numbers", "A1"]
    },
    {
      "source": "четырнадцать",
      "target": "četrpadsmit",
      "tags": ["numbers", "A1"]
    },
    {
      "source": "пятнадцать",
      "target": "piecpadsmit",
      "tags": ["numbers", "A1"]
    },
    {
      "source": "шестнадцать",
      "target": "sešpadsmit",
      "tags": ["numbers", "A1"]
    },
    {
      "source": "семнадцать",
      "target": "septiņpadsmit",
      "tags": ["numbers", "A1"]
    },
    {
      "source": "восемнадцать",
      "target": "astoņpadsmit",
      "tags": ["numbers", "A1"]
    },
    {
      "source": "девятнадцать",
      "target": "deviņpadsmit",
      "tags": ["numbers", "A1"]
    },
    {
      "source": "двадцать",
      "target": "divdesmit",
      "tags": ["numbers", "A1"]
    },
    {
      "source": "красный",
      "target": "sarkans",
      "tags": ["colours", "A1"]
    },
    {
      "source": "синий",
      "target": "zils",
      "tags": ["colours", "A1"]
    },
    {
      "source": "зелёный",
      "target": "zaļš",
      "tags": ["colours", "A1"]
    },
    {
      "source": "жёлтый",
      "target": "dzeltens",
      "tags": ["colours", "A1"]
    },
    {
      "source": "белый",
      "target": "balts",
      "tags": ["colours", "A1"]
    },
    {
      "source": "чёрный",
      "target": "melns",
      "tags": ["colours", "A1"]
    },
    {
      "source": "оранжевый",
      "target": "oranžs",
      "tags": ["colours", "A1"]
    },
    {
      "source": "розовый",
      "target": "rozā",
      "tags": ["colours", "A1"]
    },
    {
      "source": "фиолетовый",
      "target": "violets",
      "tags": ["colours", "A1"]
    },
    {
      "source": "коричневый",
      "target": "brūns",
      "tags": ["colours", "A1"]
    },
    {
      "source": "серый",
      "target": "pelēks",
      "tags": ["colours", "A1"]
    },
    {
      "source": "мама",
      "target": "māte",
      "tags": ["family", "A1"]
    },
    {
      "source": "папа",
      "target": "tēvs",
      "tags": ["family", "A1"]
    },
    {
      "source": "сестра",
      "target": "māsa",
      "tags": ["family", "A1"]
    },
    {
      "source": "брат",
      "target": "brālis",
      "tags": ["family", "A1"]
    },
    {
      "source": "бабушка",
      "target": "vecāmāte",
      "tags": ["family", "A1"]
    },
    {
      "source": "дедушка",
      "target": "vectēvs",
      "tags": ["family", "A1"]
    },
    {
      "source": "ребёнок",
      "target": "bērns",
      "tags": ["family", "A1"]
    },
    {
      "source": "сын",
      "target": "dēls",
      "tags": ["family", "A1"]
    },
    {
      "source": "дочь",
      "target": "meita",
      "tags": ["family", "A1"]
    },
    {
      "source": "муж",
      "target": "vīrs",
      "tags": ["family", "A1"]
    },
    {
      "source": "жена",
      "target": "sieva",
      "tags": ["family", "A1"]
    },
    {
      "source": "семья",
      "target": "ģimene",
      "tags": ["family", "A1"]
    },
    {
      "source": "вода",
      "target": "ūdens",
      "tags": ["food-drink", "A1"]
    },
    {
      "source": "молоко",
      "target": "piens",
      "tags": ["food-drink", "A1"]
    },
    {
      "source": "хлеб",
      "target": "maize",
      "tags": ["food-drink", "A1"]
    },
    {
      "source": "яйцо",
      "target": "ola",
      "tags": ["food-drink", "A1"]
    },
    {
      "source": "яблоко",
      "target": "ābols",
      "tags": ["food-drink", "A1"]
    },
    {
      "source": "банан",
      "target": "banāns",
      "tags": ["food-drink", "A1"]
    },
    {
      "source": "кофе",
      "target": "kafija",
      "tags": ["food-drink", "A1"]
    },
    {
      "source": "чай",
      "target": "tēja",
      "tags": ["food-drink", "A1"]
    },
    {
      "source": "сыр",
      "target": "siers",
      "tags": ["food-drink", "A1"]
    },
    {
      "source": "мясо",
      "target": "gaļa",
      "tags": ["food-drink", "A1"]
    },
    {
      "source": "рис",
      "target": "rīsi",
      "tags": ["food-drink", "A1"]
    },
    {
      "source": "сахар",
      "target": "cukurs",
      "tags": ["food-drink", "A1"]
    },
    {
      "source": "понедельник",
      "target": "pirmdiena",
      "tags": ["days", "A1"]
    },
    {
      "source": "вторник",
      "target": "otrdiena",
      "tags": ["days", "A1"]
    },
    {
      "source": "среда",
      "target": "trešdiena",
      "tags": ["days", "A1"]
    },
    {
      "source": "четверг",
      "target": "ceturtdiena",
      "tags": ["days", "A1"]
    },
    {
      "source": "пятница",
      "target": "piektdiena",
      "tags": ["days", "A1"]
    },
    {
      "source": "суббота",
      "target": "sestdiena",
      "tags": ["days", "A1"]
    },
    {
      "source": "воскресенье",
      "target": "svētdiena",
      "tags": ["days", "A1"]
    },
    {
      "source": "январь",
      "target": "janvāris",
      "tags": ["months", "A1"]
    },
    {
      "source": "февраль",
      "target": "februāris",
      "tags": ["months", "A1"]
    },
    {
      "source": "март",
      "target": "marts",
      "tags": ["months", "A1"]
    },
    {
      "source": "апрель",
      "target": "aprīlis",
      "tags": ["months", "A1"]
    },
    {
      "source": "май",
      "target": "maijs",
      "tags": ["months", "A1"]
    },
    {
      "source": "июнь",
      "target": "jūnijs",
      "tags": ["months", "A1"]
    },
    {
      "source": "июль",
      "target": "jūlijs",
      "tags": ["months", "A1"]
    },
    {
      "source": "август",
      "target": "augusts",
      "tags": ["months", "A1"]
    },
    {
      "source": "сентябрь",
      "target": "septembris",
      "tags": ["months", "A1"]
    },
    {
      "source": "октябрь",
      "target": "oktobris",
      "tags": ["months", "A1"]
    },
    {
      "source": "ноябрь",
      "target": "novembris",
      "tags": ["months", "A1"]
    },
    {
      "source": "декабрь",
      "target": "decembris",
      "tags": ["months", "A1"]
    },
    {
      "source": "быть",
      "target": "būt",
      "tags": ["verbs", "A1"]
    },
    {
      "source": "иметь",
      "target": "piederēt",
      "tags": ["verbs", "A1"]
    },
    {
      "source": "идти",
      "target": "iet",
      "tags": ["verbs", "A1"]
    },
    {
      "source": "хотеть",
      "target": "gribēt",
      "tags": ["verbs", "A1"]
    },
    {
      "source": "любить",
      "target": "patikt",
      "tags": ["verbs", "A1"]
    },
    {
      "source": "прийти",
      "target": "nākt",
      "tags": ["verbs", "A1"]
    },
    {
      "source": "видеть",
      "target": "redzēt",
      "tags": ["verbs", "A1"]
    },
    {
      "source": "слышать",
      "target": "dzirdēt",
      "tags": ["verbs", "A1"]
    },
    {
      "source": "есть",
      "target": "ēst",
      "tags": ["verbs", "A1"]
    },
    {
      "source": "пить",
      "target": "dzert",
      "tags": ["verbs", "A1"]
    },
    {
      "source": "спать",
      "target": "gulēt",
      "tags": ["verbs", "A1"]
    },
    {
      "source": "сидеть",
      "target": "sēdēt",
      "tags": ["verbs", "A1"]
    },
    {
      "source": "стоять",
      "target": "stāvēt",
      "tags": ["verbs", "A1"]
    },
    {
      "source": "говорить",
      "target": "runāt",
      "tags": ["verbs", "A1"]
    },
    {
      "source": "дать",
      "target": "dot",
      "tags": ["verbs", "A1"]
    },
    {
      "source": "взять",
      "target": "ņemt",
      "tags": ["verbs", "A1"]
    },
    {
      "source": "смотреть",
      "target": "skatīties",
      "tags": ["verbs", "A1"]
    },
    {
      "source": "хороший",
      "target": "labs",
      "tags": ["adjectives", "A1"]
    },
    {
      "source": "плохой",
      "target": "slikts",
      "tags": ["adjectives", "A1"]
    },
    {
      "source": "большой",
      "target": "liels",
      "tags": ["adjectives", "A1"]
    },
    {
      "source": "маленький",
      "target": "mazs",
      "tags": ["adjectives", "A1"]
    },
    {
      "source": "горячий",
      "target": "karsts",
      "tags": ["adjectives", "A1"]
    },
    {
      "source": "холодный",
      "target": "auksts",
      "tags": ["adjectives", "A1"]
    },
    {
      "source": "новый",
      "target": "jauns",
      "tags": ["adjectives", "A1"]
    },
    {
      "source": "старый",
      "target": "vecs",
      "tags": ["adjectives", "A1"]
    },
    {
      "source": "длинный",
      "target": "garš",
      "tags": ["adjectives", "A1"]
    },
    {
      "source": "короткий",
      "target": "īss",
      "tags": ["adjectives", "A1"]
    },
    {
      "source": "высокий",
      "target": "augsts",
      "tags": ["adjectives", "A1"]
    },
    {
      "source": "низкий",
      "target": "zems",
      "tags": ["adjectives", "A1"]
    },
    {
      "source": "я",
      "target": "es",
      "tags": ["pronouns", "A1"]
    },
    {
      "source": "ты",
      "target": "tu",
      "tags": ["pronouns", "A1"]
    },
    {
      "source": "он",
      "target": "viņš",
      "tags": ["pronouns", "A1"]
    },
    {
      "source": "она",
      "target": "viņa",
      "tags": ["pronouns", "A1"]
    },
    {
      "source": "мы",
      "target": "mēs",
      "tags": ["pronouns", "A1"]
    },
    {
      "source": "они",
      "target": "viņi",
      "tags": ["pronouns", "A1"]
    },
    {
      "source": "оно",
      "target": "tas",
      "tags": ["pronouns", "A1"]
    },
    {
      "source": "дом",
      "target": "māja",
      "tags": ["home", "A1"]
    },
    {
      "source": "комната",
      "target": "istaba",
      "tags": ["home", "A1"]
    },
    {
      "source": "дверь",
      "target": "durvis",
      "tags": ["home", "A1"]
    },
    {
      "source": "окно",
      "target": "logs",
      "tags": ["home", "A1"]
    },
    {
      "source": "стол",
      "target": "galds",
      "tags": ["home", "A1"]
    },
    {
      "source": "стул",
      "target": "krēsls",
      "tags": ["home", "A1"]
    },
    {
      "source": "кровать",
      "target": "gulta",
      "tags": ["home", "A1"]
    },
    {
      "source": "человек",
      "target": "cilvēks",
      "tags": ["social", "A1"]
    },
    {
      "source": "мужчина",
      "target": "vīrietis",
      "tags": ["social", "A1"]
    },
    {
      "source": "женщина",
      "target": "sieviete",
      "tags": ["social", "A1"]
    },
    {
      "source": "мальчик",
      "target": "zēns",
      "tags": ["social", "A1"]
    },
    {
      "source": "девочка",
      "target": "meitene",
      "tags": ["social", "A1"]
    },
    {
      "source": "друг",
      "target": "draugs",
      "tags": ["social", "A1"]
    },
    {
      "source": "имя",
      "target": "vārds",
      "tags": ["social", "A1"]
    },
    {
      "source": "возраст",
      "target": "vecums",
      "tags": ["social", "A1"]
    },
    {
      "source": "животное",
      "target": "dzīvnieks",
      "tags": ["nature", "A1"]
    },
    {
      "source": "собака",
      "target": "suns",
      "tags": ["nature", "A1"]
    },
    {
      "source": "кошка",
      "target": "kaķis",
      "tags": ["nature", "A1"]
    },
    {
      "source": "птица",
      "target": "putns",
      "tags": ["nature", "A1"]
    },
    {
      "source": "рыба",
      "target": "zivs",
      "tags": ["nature", "A1"]
    },
    {
      "source": "дерево",
      "target": "koks",
      "tags": ["nature", "A1"]
    },
    {
      "source": "цветок",
      "target": "puķe",
      "tags": ["nature", "A1"]
    },
    {
      "source": "солнце",
      "target": "saule",
      "tags": ["nature", "A1"]
    },
    {
      "source": "дождь",
      "target": "lietus",
      "tags": ["nature", "A1"]
    },
    {
      "source": "снег",
      "target": "sniegs",
      "tags": ["nature", "A1"]
    },
    {
      "source": "телефон",
      "target": "telefons",
      "tags": ["objects", "A1"]
    },
    {
      "source": "книга",
      "target": "grāmata",
      "tags": ["objects", "A1"]
    },
    {
      "source": "ручка",
      "target": "pildspalva",
      "tags": ["objects", "A1"]
    },
    {
      "source": "сумка",
      "target": "soma",
      "tags": ["objects", "A1"]
    },
    {
      "source": "ключ",
      "target": "atslēga",
      "tags": ["objects", "A1"]
    },
    {
      "source": "деньги",
      "target": "nauda",
      "tags": ["objects", "A1"]
    },
    {
      "source": "магазин",
      "target": "veikals",
      "tags": ["social", "A1"]
    },
    {
      "source": "школа",
      "target": "skola",
      "tags": ["social", "A1"]
    },
    {
      "source": "машина",
      "target": "auto",
      "tags": ["travel", "A1"]
    },
    {
      "source": "автобус",
      "target": "autobuss",
      "tags": ["travel", "A1"]
    },
    {
      "source": "улица",
      "target": "iela",
      "tags": ["travel", "A1"]
    },
    {
      "source": "город",
      "target": "pilsēta",
      "tags": ["travel", "A1"]
    },
    {
      "source": "страна",
      "target": "valsts",
      "tags": ["travel", "A1"]
    },
    {
      "source": "здесь",
      "target": "šeit",
      "tags": ["directions", "A1"]
    },
    {
      "source": "там",
      "target": "tur",
      "tags": ["directions", "A1"]
    },
    {
      "source": "направо",
      "target": "pa labi",
      "tags": ["directions", "A1"]
    },
    {
      "source": "налево",
      "target": "pa kreisi",
      "tags": ["directions", "A1"]
    },
    {
      "source": "прямо",
      "target": "taisni",
      "tags": ["directions", "A1"]
    },
    {
      "source": "вверх",
      "target": "augšā",
      "tags": ["directions", "A1"]
    },
    {
      "source": "вниз",
      "target": "lejā",
      "tags": ["directions", "A1"]
    },
    {
      "source": "день",
      "target": "diena",
      "tags": ["time", "A1"]
    },
    {
      "source": "ночь",
      "target": "nakts",
      "tags": ["time", "A1"]
    },
    {
      "source": "утро",
      "target": "rīts",
      "tags": ["time", "A1"]
    },
    {
      "source": "вечер",
      "target": "vakars",
      "tags": ["time", "A1"]
    },
    {
      "source": "сейчас",
      "target": "tagad",
      "tags": ["time", "A1"]
    },
    {
      "source": "вчера",
      "target": "vakar",
      "tags": ["time", "A1"]
    },
    {
      "source": "завтра",
      "target": "rīt",
      "tags": ["time", "A1"]
    },
    {
      "source": "сегодня",
      "target": "šodien",
      "tags": ["time", "A1"]
    },
    {
      "source": "неделя",
      "target": "nedēļa",
      "tags": ["time", "A1"]
    },
    {
      "source": "месяц",
      "target": "mēnesis",
      "tags": ["time", "A1"]
    },
    {
      "source": "год",
      "target": "gads",
      "tags": ["time", "A1"]
    },
    {
      "source": "голова",
      "target": "galva",
      "tags": ["body", "A1"]
    },
    {
      "source": "рука",
      "target": "roka",
      "tags": ["body", "A1"]
    },
    {
      "source": "нога",
      "target": "kāja",
      "tags": ["body", "A1"]
    },
    {
      "source": "глаза",
      "target": "acis",
      "tags": ["body", "A1"]
    },
    {
      "source": "уши",
      "target": "ausis",
      "tags": ["body", "A1"]
    },
    {
      "source": "нос",
      "target": "deguns",
      "tags": ["body", "A1"]
    },
    {
      "source": "рот",
      "target": "mute",
      "tags": ["body", "A1"]
    },
    {
      "source": "сердце",
      "target": "sirds",
      "tags": ["body", "A1"]
    }
  ]
}
